django_kobo_exporter-1.1.1.dist-info/licenses/LICENSE
kobo_exporter/__init__.py
kobo_exporter/apps.py
kobo_exporter/django_compat.py
kobo_exporter/urls.py
kobo_exporter/views.py
tests/test_app/__init__.py
tests/test_app/urls.py
django_kobo_exporter-1.1.1.dist-info/METADATA
django_kobo_exporter-1.1.1.dist-info/WHEEL
django_kobo_exporter-1.1.1.dist-info/top_level.txt
django_kobo_exporter-1.1.1.dist-info/RECORD
