Metadata-Version: 2.4
Name: django-kobo-exporter
Version: 1.1.1
Summary: Prometheus exporter for kobo hub
Home-page: https://github.com/release-engineering/django-kobo-exporter
License: GPLv3
Project-URL: Changelog, https://github.com/release-engineering/django-kobo-exporter/blob/master/CHANGELOG.md
Classifier: Development Status :: 4 - Beta
Classifier: Intended Audience :: Developers
Classifier: License :: OSI Approved :: GNU General Public License v3 or later (GPLv3+)
Classifier: Programming Language :: Python :: 3
Classifier: Framework :: Django
Requires-Python: >=3.6
License-File: LICENSE
Requires-Dist: django
Requires-Dist: prometheus-client
Requires-Dist: kobo
Dynamic: classifier
Dynamic: description
Dynamic: description-content-type
Dynamic: home-page
Dynamic: license
Dynamic: license-file
Dynamic: project-url
Dynamic: requires-dist
Dynamic: requires-python
Dynamic: summary
